{
  "id": "f20211bf-8c95-415a-a952-10f22c2be1ed",
  "prevId": "00000000-0000-0000-0000-000000000000",
  "version": "7",
  "dialect": "postgresql",
  "tables": {
    "public.feedback": {
      "name": "feedback",
      "schema": "",
      "columns": {
        "id": {
          "name": "id",
          "type": "serial",
          "primaryKey": true,
          "notNull": true
        },
        "opportunity_id": {
          "name": "opportunity_id",
          "type": "integer",
          "primaryKey": false,
          "notNull": true
        },
        "action": {
          "name": "action",
          "type": "feedback_action",
          "typeSchema": "public",
          "primaryKey": false,
          "notNull": true
        },
        "timestamp": {
          "name": "timestamp",
          "type": "timestamp",
          "primaryKey": false,
          "notNull": true,
          "default": "now()"
        },
        "notes": {
          "name": "notes",
          "type": "text",
          "primaryKey": false,
          "notNull": false
        }
      },
      "indexes": {},
      "foreignKeys": {
        "feedback_opportunity_id_opportunities_id_fk": {
          "name": "feedback_opportunity_id_opportunities_id_fk",
          "tableFrom": "feedback",
          "tableTo": "opportunities",
          "columnsFrom": [
            "opportunity_id"
          ],
          "columnsTo": [
            "id"
          ],
          "onDelete": "no action",
          "onUpdate": "no action"
        }
      },
      "compositePrimaryKeys": {},
      "uniqueConstraints": {},
      "policies": {},
      "checkConstraints": {},
      "isRLSEnabled": false
    },
    "public.opportunities": {
      "name": "opportunities",
      "schema": "",
      "columns": {
        "id": {
          "name": "id",
          "type": "serial",
          "primaryKey": true,
          "notNull": true
        },
        "type": {
          "name": "type",
          "type": "opportunity_type",
          "typeSchema": "public",
          "primaryKey": false,
          "notNull": true
        },
        "source": {
          "name": "source",
          "type": "source",
          "typeSchema": "public",
          "primaryKey": false,
          "notNull": true
        },
        "origin": {
          "name": "origin",
          "type": "text",
          "primaryKey": false,
          "notNull": false
        },
        "received_at": {
          "name": "received_at",
          "type": "timestamp",
          "primaryKey": false,
          "notNull": true,
          "default": "now()"
        },
        "canonical_url": {
          "name": "canonical_url",
          "type": "text",
          "primaryKey": false,
          "notNull": false
        },
        "source_url": {
          "name": "source_url",
          "type": "text",
          "primaryKey": false,
          "notNull": false
        },
        "title": {
          "name": "title",
          "type": "text",
          "primaryKey": false,
          "notNull": true
        },
        "company": {
          "name": "company",
          "type": "text",
          "primaryKey": false,
          "notNull": false
        },
        "industry": {
          "name": "industry",
          "type": "text",
          "primaryKey": false,
          "notNull": false
        },
        "location": {
          "name": "location",
          "type": "text",
          "primaryKey": false,
          "notNull": false
        },
        "country": {
          "name": "country",
          "type": "text",
          "primaryKey": false,
          "notNull": false
        },
        "remote_status": {
          "name": "remote_status",
          "type": "text",
          "primaryKey": false,
          "notNull": false
        },
        "salary_text": {
          "name": "salary_text",
          "type": "text",
          "primaryKey": false,
          "notNull": false
        },
        "employment_type": {
          "name": "employment_type",
          "type": "text",
          "primaryKey": false,
          "notNull": false
        },
        "description": {
          "name": "description",
          "type": "text",
          "primaryKey": false,
          "notNull": false
        },
        "requirements": {
          "name": "requirements",
          "type": "text",
          "primaryKey": false,
          "notNull": false
        },
        "closing_date": {
          "name": "closing_date",
          "type": "timestamp",
          "primaryKey": false,
          "notNull": false
        },
        "fit_score": {
          "name": "fit_score",
          "type": "integer",
          "primaryKey": false,
          "notNull": false,
          "default": 0
        },
        "confidence": {
          "name": "confidence",
          "type": "confidence",
          "typeSchema": "public",
          "primaryKey": false,
          "notNull": false,
          "default": "'MEDIUM'"
        },
        "reasons": {
          "name": "reasons",
          "type": "jsonb",
          "primaryKey": false,
          "notNull": false
        },
        "concerns": {
          "name": "concerns",
          "type": "jsonb",
          "primaryKey": false,
          "notNull": false
        },
        "tags": {
          "name": "tags",
          "type": "jsonb",
          "primaryKey": false,
          "notNull": false
        },
        "recommended_action": {
          "name": "recommended_action",
          "type": "recommended_action",
          "typeSchema": "public",
          "primaryKey": false,
          "notNull": false,
          "default": "'STORE'"
        },
        "status": {
          "name": "status",
          "type": "opportunity_status",
          "typeSchema": "public",
          "primaryKey": false,
          "notNull": false,
          "default": "'NEW'"
        },
        "created_at": {
          "name": "created_at",
          "type": "timestamp",
          "primaryKey": false,
          "notNull": true,
          "default": "now()"
        },
        "updated_at": {
          "name": "updated_at",
          "type": "timestamp",
          "primaryKey": false,
          "notNull": true,
          "default": "now()"
        }
      },
      "indexes": {},
      "foreignKeys": {},
      "compositePrimaryKeys": {},
      "uniqueConstraints": {
        "opportunities_canonical_url_unique": {
          "name": "opportunities_canonical_url_unique",
          "nullsNotDistinct": false,
          "columns": [
            "canonical_url"
          ]
        }
      },
      "policies": {},
      "checkConstraints": {},
      "isRLSEnabled": false
    },
    "public.settings": {
      "name": "settings",
      "schema": "",
      "columns": {
        "key": {
          "name": "key",
          "type": "text",
          "primaryKey": true,
          "notNull": true
        },
        "value": {
          "name": "value",
          "type": "jsonb",
          "primaryKey": false,
          "notNull": true
        },
        "updated_at": {
          "name": "updated_at",
          "type": "timestamp",
          "primaryKey": false,
          "notNull": true,
          "default": "now()"
        }
      },
      "indexes": {},
      "foreignKeys": {},
      "compositePrimaryKeys": {},
      "uniqueConstraints": {},
      "policies": {},
      "checkConstraints": {},
      "isRLSEnabled": false
    }
  },
  "enums": {
    "public.confidence": {
      "name": "confidence",
      "schema": "public",
      "values": [
        "LOW",
        "MEDIUM",
        "HIGH"
      ]
    },
    "public.feedback_action": {
      "name": "feedback_action",
      "schema": "public",
      "values": [
        "LIKE",
        "DISLIKE",
        "IGNORE_COMPANY",
        "IGNORE_SENDER",
        "MORE_LIKE_THIS",
        "LESS_LIKE_THIS",
        "APPLIED",
        "SAVED"
      ]
    },
    "public.opportunity_status": {
      "name": "opportunity_status",
      "schema": "public",
      "values": [
        "NEW",
        "SENT",
        "SAVED",
        "DISMISSED",
        "APPLIED"
      ]
    },
    "public.opportunity_type": {
      "name": "opportunity_type",
      "schema": "public",
      "values": [
        "JOB",
        "BUSINESS",
        "NOISE"
      ]
    },
    "public.recommended_action": {
      "name": "recommended_action",
      "schema": "public",
      "values": [
        "ALERT",
        "DIGEST",
        "STORE"
      ]
    },
    "public.source": {
      "name": "source",
      "schema": "public",
      "values": [
        "EMAIL",
        "RSS",
        "WEB"
      ]
    }
  },
  "schemas": {},
  "sequences": {},
  "roles": {},
  "policies": {},
  "views": {},
  "_meta": {
    "columns": {},
    "schemas": {},
    "tables": {}
  }
}